{"v": 1, "creeLe": 1783858103185, "dernierArbitrage": 1783915374197, "cashEUR": 290.29999999999995, "fx": 1.1422, "positions": {"QQQ": {"qty": 3.5866326584169217, "costEUR": 2281.0578841125043}, "GOOGL": {"qty": 6.267614790105704, "costEUR": 1962.435692600653}, "EEM": {"qty": 32.10776377268826, "costEUR": 1882.9647130127312}, "AAPL": {"qty": 6.518268139536503, "costEUR": 1801.7301428044566}, "NVDA": {"qty": 9.63346503180929, "costEUR": 1781.5115674696547}}, "bench": {"p0": 754.95, "fx0": 1.1419}, "stats": {"clotures": 0, "gagnants": 0, "realise": 0.0, "frais": 9.7}, "histo": [{"t": 1783858103185, "eq": 9990.3, "bench": 10000.0}, {"t": 1783864703516, "eq": 9990.3, "bench": 10000.0}, {"t": 1783869494131, "eq": 9990.3, "bench": 10000.0}, {"t": 1783877229751, "eq": 9990.3, "bench": 10000.0}, {"t": 1783884814687, "eq": 9999.65, "bench": 10009.64}, {"t": 1783890514033, "eq": 10003.91, "bench": 10014.03}, {"t": 1783894154980, "eq": 10012.44, "bench": 10022.82}, {"t": 1783897857686, "eq": 10007.32, "bench": 10017.55}, {"t": 1783901556904, "eq": 10002.21, "bench": 10012.28}, {"t": 1783915374197, "eq": 10005.61, "bench": 10015.79}, {"t": 1783928518617, "eq": 9987.75, "bench": 9997.37}], "trades": [{"t": 1783858103185, "sym": "QQQ", "nom": "Nasdaq 100", "cat": "ETF", "sens": "ACHAT", "qty": 3.5866326584169217, "px": 725.51, "fx": 1.1419, "valEUR": 2278.779105007497, "frais": 2.278779105007497, "pnl": null, "raison": "Entrée momentum · rang 2"}, {"t": 1783858103185, "sym": "GOOGL", "nom": "Alphabet", "cat": "Action", "sens": "ACHAT", "qty": 6.267614790105704, "px": 357.18, "fx": 1.1419, "valEUR": 1960.4752173832699, "frais": 1.9604752173832698, "pnl": null, "raison": "Entrée momentum · rang 5"}, {"t": 1783858103185, "sym": "EEM", "nom": "Marchés émergents", "cat": "ETF", "sens": "ACHAT", "qty": 32.10776377268826, "px": 66.9, "fx": 1.1419, "valEUR": 1881.083629383348, "frais": 1.881083629383348, "pnl": null, "raison": "Entrée momentum · rang 3"}, {"t": 1783858103185, "sym": "AAPL", "nom": "Apple", "cat": "Action", "sens": "ACHAT", "qty": 6.518268139536503, "px": 315.32, "fx": 1.1419, "valEUR": 1799.9302125918648, "frais": 1.7999302125918648, "pnl": null, "raison": "Entrée momentum · rang 1"}, {"t": 1783858103185, "sym": "NVDA", "nom": "Nvidia", "cat": "Action", "sens": "ACHAT", "qty": 9.63346503180929, "px": 210.96, "fx": 1.1419, "valEUR": 1779.7318356340206, "frais": 1.7797318356340206, "pnl": null, "raison": "Entrée momentum · rang 4"}], "lastPx": {"AAPL": {"px": 315.32, "prev": 316.22, "jour": 20647}, "MSFT": {"px": 385.1, "prev": 384.36, "jour": 20647}, "NVDA": {"px": 210.96, "prev": 202.78, "jour": 20647}, "GOOGL": {"px": 357.18, "prev": 358.89, "jour": 20647}, "AMZN": {"px": 245.34, "prev": 247.04, "jour": 20647}, "META": {"px": 669.21, "prev": 631.48, "jour": 20647}, "JPM": {"px": 336.47, "prev": 335.47, "jour": 20647}, "SPY": {"px": 754.95, "prev": 751.71, "jour": 20647}, "QQQ": {"px": 725.51, "prev": 723.28, "jour": 20647}, "EEM": {"px": 66.9, "prev": 66.78, "jour": 20647}, "TLT": {"px": 84.47, "prev": 84.49, "jour": 20647}, "EZU": {"px": 68.56, "prev": 68.51, "jour": 20647}, "GLD": {"px": 377.01, "prev": 378.18, "jour": 20647}, "SLV": {"px": 53.95, "prev": 54.14, "jour": 20647}, "USO": {"px": 108.7, "prev": 109.01, "jour": 20647}, "DBC": {"px": 27.52, "prev": 27.58, "jour": 20647}}, "journal": [{"t": 1783915374197, "msg": "Portefeuille déjà aligné — aucun ordre"}, {"t": 1783884814687, "msg": "Portefeuille déjà aligné — aucun ordre"}, {"t": 1783858103185, "msg": "5 ordres exécutés"}, {"t": 1783858103185, "msg": "Bot initialisé · capital 10 000 €"}], "majLe": 1783928518617, "schema": 2, "signaux": [{"s": "AAPL", "mom": 0.21389907054283197, "trend": true, "vol": 0.3498, "px": 315.32, "prev": 316.22, "cible": 0.18}, {"s": "USO", "mom": 0.20591184620284736, "trend": false, "vol": 0.404, "px": 108.7, "prev": 109.01, "cible": 0}, {"s": "QQQ", "mom": 0.17828453728670035, "trend": true, "vol": 0.2763, "px": 725.51, "prev": 723.28, "cible": 0.2279}, {"s": "EEM", "mom": 0.1405283586125069, "trend": true, "vol": 0.3347, "px": 66.9, "prev": 66.78, "cible": 0.1881}, {"s": "NVDA", "mom": 0.12922885908241522, "trend": true, "vol": 0.3538, "px": 210.96, "prev": 202.78, "cible": 0.178}, {"s": "GOOGL", "mom": 0.1117139359981314, "trend": true, "vol": 0.3212, "px": 357.18, "prev": 358.89, "cible": 0.196}, {"s": "SPY", "mom": 0.10300545640641068, "trend": true, "vol": 0.135, "px": 754.95, "prev": 751.71, "cible": 0}, {"s": "DBC", "mom": 0.08420561894246109, "trend": false, "vol": 0.1813, "px": 27.52, "prev": 27.58, "cible": 0}, {"s": "JPM", "mom": 0.05304888202369584, "trend": true, "vol": 0.2451, "px": 336.47, "prev": 335.47, "cible": 0}, {"s": "META", "mom": 0.04915339291240717, "trend": true, "vol": 0.5632, "px": 669.21, "prev": 631.48, "cible": 0}, {"s": "EZU", "mom": 0.038393297055075326, "trend": true, "vol": 0.1633, "px": 68.56, "prev": 68.51, "cible": 0}, {"s": "AMZN", "mom": 0.012669919414327602, "trend": true, "vol": 0.3405, "px": 245.34, "prev": 247.04, "cible": 0}, {"s": "TLT", "mom": -0.028163054144385524, "trend": false, "vol": 0.0937, "px": 84.47, "prev": 84.49, "cible": 0}, {"s": "MSFT", "mom": -0.0780837910874268, "trend": false, "vol": 0.3692, "px": 385.1, "prev": 384.36, "cible": 0}, {"s": "GLD", "mom": -0.11066325082741507, "trend": false, "vol": 0.224, "px": 377.01, "prev": 378.18, "cible": 0}, {"s": "SLV", "mom": -0.22255044826706583, "trend": false, "vol": 0.4503, "px": 53.95, "prev": 54.14, "cible": 0}]}